{"PhotonId":"C40109B1CB88A85B","UserName":"1","AccountCreationDate":"2023-06-29","PlayerProps":{"didTutorial":true},"AllowedCosmetics":["LBAJB","LMANT","LBAJC","LFAEW","LHAAP","LBAIK","LFAAB","LFAEF","LBAGE","LBAGA","LMAJH","LMAJI","LMAJB","LSABJ","LHAFW","LBAFY","LBAGD","LBADD","LHADO","LBAFN","LHAFO","LBAFL","LMAIL","LBAET","LBAEO","LBAAR","LHABP","LHAAZ","LFADF","LHAAB","LMAGG","LMABP","LMAGO","LHAEM","LSABC","LBADV","LMAFN","LBAEA","LHAAD","LFAAL","LHAAE","LBAAB","LHAAC","LFAAJ","LFAAC",""]}