{"PhotonId":"593C7801700B5199","UserName":"AIRAVR","AccountCreationDate":"2023-08-13","PlayerProps":{"BarkVersion":"1.5.2","didTutorial":true,"BarkPlayerSize":1.0,"G_Tag":1,"G_Shirt":"None","BarkEnabledModules":{"Airplane":false,"Bubble":false,"Fly":false,"Grappling Hooks":false,"Platforms":true,"Nail Gun":false,"Rockets":false,"Speed Boost":true,"Wall Run":false,"Zipline":false,"Gravity":false,"No Collide":false,"No Slip":false,"Potions":false,"Slippery Hands":false,"Checkpoint":false,"Pearl":false,"Teleport":false,"Boxing":false,"Piggyback":false,"Telekinesis":false,"Fireflies":false,"X-Ray":false,"Join Bark Code":false,"Halo":false}},"AllowedCosmetics":["ITEMS","LBAAJ","LHAAP","LBAGP","LBAGO","LBAGN","LBADA","LBAGE","LFADP","LHAFU","LHABP","game-purchase-bundleLBAFV","LHACZ","LBAAF","LBAFL","LMAIL","LBAFN","LFAAM","LHAAB","LBAET","LFAAJ","LBABH","LFADK","LBAEO","LHAAM","LHAAD","LHAAL","LMABA","LSAAC","LHAAX","LBAAN","LFAAT","LMAGR","LSABD","LHAEV","LBAEF","LHAAN","LFADF","LFAAH","LBAAC","LBAEB","LBAEA","LFAAI","LFAAN","LHAAE","LBAAB","LFAAL","LBADB","LHAAC","LBADS",""]}