{"PhotonId":"825AD97FC0668299","UserName":"BETH","AccountCreationDate":"2021-11-27","PlayerProps":{"didTutorial":true},"AllowedCosmetics":["LBAJJ","LFAEW","LHABG","LBAJC","LBAIU","LHAAS","LBAIR","LBAIK","LMALU","LBAHY","LHAAJ","LBAHV","LHAGW","LBAHP","LBAHF","LFAEG","LBAGY","LBAGO","LFACI","LBAGE","LBAFV","LFACE","LBAFL","LBAFN","LMAIL","LBAET","LFADK","LBAEO","LFABW","LMAAT","LFAAT","LHAAX","LBAAN","LSAAC","LHABP","LFADF","LBAEB","LBAEA","LMACA","LFACY","LBADS","LFABO","LFACP","LHAAR","LBADL","LHAEB","LHAAB","LBADC","LBAAF","LHAAD","LBADB","LFAAH","LFAAC","LBACD","LFAAL","LBACT","LFAAN","LMACT","LBACQ","LHAAM","LHAAQ","LHAAP","LHAAE","LFABX","LBAAB","LHAAC","LHAAL","LFABF",""]}