{"PhotonId":"1500C51A984FD60A","UserName":"BINLY","AccountCreationDate":"2021-12-25","PlayerProps":{"didTutorial":true},"AllowedCosmetics":["LFAEW","LBAJC","LBAIR","LFAEE","LHAAQ","LSABN","LHAGO","LBAGY","LBAGT","LBAFB","LBAGE","LBAGD","LBAFL","LBAFN","LMAIL","LBAEX","LFACD","LHAAS","LBAET","LBACM","LHADD","LBAES","LSABE","LHAFG","LMAHJ","LBACJ","LBAEO","LFADK","LFADF","LMAAR","LBADY","LHAAH","LBADS","LBACD","LFACL","LMADW","LBADB","LHABM","LHABI","LHABD","LSAAE","LFAAX","LHABR","LFABD","LMABI","LBACT","LBAAU","LBACQ","LMACT","LHACY","LFAAY","LHABG","LBACI","LSAAQ","LHADF","LFAAO","LMACI","LHADE","LSAAP","LBACH","LFABZ","LMABZ","LHADA","LBACF","LSAAP2","LFABX","LHACU","LSAAN","LBACC","LMABR","LBAAH","LHABP","LBAAQ","LFAAW","LBAAP","LMAAT","LMABO","LHAAT","LHAAZ","LFAAT","LSAAC","LHAAX","LBAAN","LHAAV","LSAAA","LFAAR","LBAAL","LFAAS","LSAAB","LBAAM","LHAAW","LBAAO","LSAAD","LHAAY","LFAAU","LMAAZ","LFAAB","LBAAJ","LFAAH","LFAAI","LHAAF","LFABK","LFAAA","LMAAN","LFABN","LHAAB","LHAAJ","LFAAJ","LBAAF","LHABC","LBABH","LFAAF","LBAAC","LMAAF","LFABH","LHABZ","LFAAL","LBAAA","LFABF","LHAAC","LHAAR","LBAAZ","LBABA","LHAAE","LFABB","Early Access Supporter PackLBAAB","LFABA","LHAAD","LBAAE","LFAAM","LFAAN","LHAAA","LHAAK","LHAAL","LHAAM","LHAAN","LHAAO","LHAAP","LHABA","LHABB",""]}