{"PhotonId":"21A8EEFE7BF065A","UserName":"BMMDUKEZ","AccountCreationDate":"2023-05-01","PlayerProps":{"didTutorial":true},"AllowedCosmetics":["LFAAY","LMANO","LFAEW","LMACH","LBAHY","LBABO","LMAAM","LHAEF","LSABM","LHAGF","LBAGU","LBADL","LBAGN","LFABI","LHAAM","LBAGE","LFABE","LHABZ","LBAGD","LHABP","LHAAN","LFABF","LBABF","LBAFV","LFADP","LHABR","LMAIL","LBAFN","LBAFL","LFACD","LHABI","LFABB","LBAAT","LHABC","LBAEX","LHAAG","LFAAF","LBAEU","LMAHU","LHAFJ","LSABF","LBAET","LBAAG","LBAEP","LHABD","LSAAE","LFAAX","LBAAR","LMAHJ","LSABE","LHAFG","LBAES","LFADK","LBAEO","LBAEN","LMADS","LMABB","LHAAZ","LMABC","LMAAW","LMAAZ","LBAAN","LHAAX","LFAAT","LSAAC","LMAGX","LBAAB","LMAGS","LHAEV","LBAEF","LSABD","LMAGR","LFAAG","LFADF","LHAEW","LMAGY","LBAEG","LMAGP","LMAGQ","LBAEB","LBAEA","LHACS","LMAGA","LMAFX","LBADB","LBADS","LHAEK","LHAAP","LBABN","LFAAN","LHAAC",""]}