{"PhotonId":"CA8FDFF42B7A1836","UserName":"BROKENSTONE","AccountCreationDate":"2022-02-07","PlayerProps":{"BananaOS":"1.0.9","didTutorial":true},"AllowedCosmetics":["LBAKA","LBAJN","LMAOG","LDAAD","LBAJO","LMAKE","LBAJB","LBAIU","LBAJJ","LMANG","LFAEW","LBAJC","LBAGT","LBAIR","LHACQ","LBAIK","LBAHV","LBAHY","LBAHP","LBAHF","LBAGZ","LBADO","LMAJA","LBAGP","LBAGO","LBAGN","LMAJT","LBAGH","LBAGE","LBAGD","LHABX","LBAFV","LBAFN","LBAFL","LMAIL","LFADL","LBAET","LBAAR","LFADK","LBAAB","LBAEO","LHAFB","LFADF","LBAEB","LBAEA","LMABV","LHAEL","LMAFK","LBADS","LHAAB","LMAFI","LMAAF","LHAAS","LBADC","LBADB","LBACT","LMACT","LBACQ","LFABX","Early Access Supporter PackLMABO","LBAAP","LFAAW","LMAAZ","LFABN","LHAAN","LFABF","LBAAE","LFAAM","LFAAN","LHAAA","LHAAK","LHAAL","LHAAM","LHAAN","LHAAO","LHAAP","LHABA","LHABB",""]}