{"PhotonId":"80BC90FF20293926","UserName":"DAISY09","AccountCreationDate":"2023-12-16","PlayerProps":{"didTutorial":true},"AllowedCosmetics":["LFAEW","LBAJC","LFAEV","LSAAE","LFAAX","LHABD","LBAIK","LHAAT","LFABS","LSAAC","LHAAX","LFAAT","LBAAN","LBAHV","LBAHP","LFADA","LFAEG","LBAHF","LFACU","LHACY","LMAKW","LBAGY","LFACP","LFABN","LSABN","LMAKG","LHAAK","LBAAH","LBAGT","LBADK","LBAGO","LBAGP","LBAGN","LHABP","LBAGE","LHACW","LHAAL","LHAFX","LFADT","LHAAG","LBAFY","LSABJ","LHAFW","LMAJB","LFAAG","LFAAA","LHAAA","LBAGD","LFAAH","LFAAN","LFAAL","LBAAB","LBAAG","LHAAP","LHAAC","LBAFR",""]}