{"PhotonId":"D2C33DCEFE6F6D4D","UserName":"ECHOFRIENDS","AccountCreationDate":"2023-06-29","PlayerProps":{"didTutorial":true},"AllowedCosmetics":["LHAAL","LHAIA","LBAJN","LMAOG","LDAAD","LBAJB","LHABK","LBAGO","LBAGN","LBAGP","LBAJC","LBACA","LFAEW","LFAAG","LFABI","LBAGD","LFADO","LBAFB","LMAIL","LBAFN","LBAFL","LBACO","LMABP","LHAAD","LBAET","LHAAI","LHAAN","LHAAA","LHAAB","LFADK","LFAAH","LFAAJ","LBAEO","LMAAR","LBAAJ","LFAAN","LHAAE","LFADF","LHAAP","LBAEA","LHAAC","LBAEB","LBADB","LFAAM","LBAAB",""]}