{"PhotonId":"775B4FBFCE4612B4","UserName":"EGG","AccountCreationDate":"2022-03-19","PlayerProps":{"didTutorial":true},"AllowedCosmetics":["LFAEW","LBAJC","LMAND","LBAHY","LBAHP","LBAHQ","LBAHF","LBAGT","LMAFG","LMAKJ","LBAGO","LBAGN","LMAJM","LSABK","LBAGF","LHAGB","LBAGE","LBAGD","LFADP","LMAAB","LMAIW","LHAFQ","LBAFS","LSABH","LMAIQ","LHAAB","LMAIV","LMAIT","LBAFV","LMAII","LMAIH","LHAFK","LMAIG","LSABG","LBAFI","LBAAW","LBAFL","LMAIL","LBAFN","LHADI","LFACD","LBAET","LMAHY","LMAHV","LBAEU","LHAFJ","LSABF","LMAHU","LFAAX","LSAAE","LHABD","LBAAS","LMACJ","LHACZ","LMAHN","LBACH","LHADE","LFABZ","LSAAP","LMACD","LMACK","LBAES","LMAHJ","LHAFG","LSABE","LFADK","LBAEO","LMABN","LFAAW","LMABG","LMABM","LBAAP","LMAHB","LBADB","LHAEV","LSABD","LMAGR","LBAEF","LMAAT","LHAAI","LFABH","LFAAL","LHAAL","LFABF","LHAAC",""]}