{"PhotonId":"E2096D12B5DEAB4C","UserName":"FANCYPANTS","AccountCreationDate":"2021-10-30","PlayerProps":{"didTutorial":true},"AllowedCosmetics":["LHAAN","LBAIK","LMAML","LMAMK","LHAHJ","LFAES","LBAIH","LBAII","LMAMM","LSABT","LHAHD","LBAIB","LMAMA","LSABR","LMALP","LBAHT","LHAGT","LBAHP","LFABP","LBAHF","LBAGT","LMAJP","LMAJJ","LSABK","LBAGF","LHAGB","LBAGE","LMAEA","LBAFW","LHAFV","LBAFX","LMAIQ","LBAFS","LHAFQ","LSABH","LBAFV","LFAAG","LFADF","LBADS","LFACL","LBADC","LBADB","LHAAB","LBACQ","LMACT","LBAAB","LFAAM","LHACY","LFABX","LHAAD",""]}