{"PhotonId":"BC4DEB810ECEC601","UserName":"GORILLA","AccountCreationDate":"2023-07-29","PlayerProps":{"didTutorial":true},"AllowedCosmetics":["LBAJO","LBAJB","LHABI","LBAJJ","LHABG","LMANO","LFAEW","LBAJC","LBAIU","LBAIR","LBAIK","LBAHY","LFAEH","LMALU","LBAHV","LBAHP","LBAHF","LBAGY","LBAGT","LBADL","LBAGN","LBAGO","LBAGP","LBAGE","LMABT","LHABZ","LBAGD","LBAFV","LMAIL","LBAFN","LBAFL","LBAET","LBACH","LFABZ","LHADE","LSAAP","LFAAX","LHABD","LSAAE","LBAAR","LSABE","LBAES","LMAHJ","LHAFG","LMAHN","LFADK","LBAEO","LHAAZ","LFAAP","LBAAO","LFAAU","LHAAY","LSAAD","LSAAM","LHACN","LBABZ","LMAAW","LBABX","LHACM","LFABU","LSAAI","LHACJ","LHAAV","LSAAA","LBAAL","LFAAR","LBAAM","LHAAW","LSAAB","LFAAS","LHAAX","LFAAT","LBAAN","LSAAC","LBADB","LBAEG","LFADH","LHAEW","LFADG","LMAGX","LMAGU","LHAEX","LFAAG","LHAAJ","LMAGZ","LMAGY","LMAGV","LMAGW","LBAEH","LMAGS","LBAEI","LFADF","LMAGQ","LHAAL","LBAAC","LHAAD","LHAAP","LMAGK","LMAGH","LMAGM","LBAEA","LHAAC",""]}