{"PhotonId":"748DD9F8436366EF","UserName":"GUYWIGGLES","AccountCreationDate":"2022-07-24","PlayerProps":{"didTutorial":true},"AllowedCosmetics":["LBAJB","LBAJJ","LMALW","LBAIA","LMALX","LDAAB","LFAEW","LBAJC","LBAIU","LBAIR","LBAIK","LBAHY","LBAHV","LBAHP","LFADA","LBAHF","LHAAE","LBAGY","LBAAB","LFACP","LBADO","LSABN","LBAGT","LBAGN","LBAGO","LBAGP","LFABI","LBAGE","LHABS","LMAJA","LSABI","LBAGD","LFABC","LHAAQ","LMAAA","LBAFS","LSABH","LHAFQ","LMAIQ","LMAIR","LBAFV","LHAFM","LBAFN","LBAFL","LMAIL","LMACM","LHABI","LBACA","LBAET","LMABP","LBAEO","LBADB","LHAAC",""]}