{"PhotonId":"709FF03FF8570500","UserName":"JOLLYKINGDUC","AccountCreationDate":"2022-05-30","PlayerProps":{"didTutorial":true},"AllowedCosmetics":["LBAIY","LBAIU","LHAAN","LBAIR","LBAIK","LBAHY","LHAAZ","LBAHV","LHAGY","LBAHP","LFAEF","LSABQ","LMALI","LHAGS","LHAGR","LMAKX","LMALA","LSABP","LBAHE","LFAED","LMALH","LBAHF","LFAEG","LMAKT","LHAAJ","LBAHD","LFACY","LHAAI","LBAGY","LBADO","LSABN","LFACP","LMAKK","LBAGT","LHAAF","LBADI","LBAGP","LBAGO","LBAGN","LMAAK","LBABN","LFABI","LHAGC","LSABK","LBAGF","LHAGB","LMAJJ","LBAGE","LHAAE","LMAJA","LSABI","LBAGD","LHACA","LBAFV","LFAAN","LBABH","LBAFL","LBAFN","LMAIL","LMACS","LBAEW","LBAET","LFACA","LHADC","LBACK","LSAAR","LMAHN","LMAHM","LBAES","LSABE","LHAFG","LMAHJ","LFADK","LBAEO","LHAEZ","LHAEW","LFADF","LBAEB","LBAEE","LBAEA","LHAAA","LMACA","LMABS","LBADZ","LHABC","LMAFU","LMAFW","LBADB","LFADC","LFABP","LFACX","LMAFP","LMAFS","LHAEM","LMAFN","LSABC","LBADV","LBADS","LBACD","LFAAH","LHAAP","LBADK","LBADC","LBAAB","LBACQ","LMACT","LHAAC","LFAAJ","LHACY","LHAAD",""]}