{"PhotonId":"ABDA8FDEE38B8245","UserName":"LIGMABOY","AccountCreationDate":"2024-11-03","PlayerProps":{"didTutorial":true},"AllowedCosmetics":["LBAJR","LHAIA","LBAJN","LMAOG","LDAAD","LBAJO","LBAJB","LBAAB","LHAAP","LBAJJ","LBAIT","LSAAP","LHADE","LBACH","LFABZ","LSAAR","LHADC","LBACK","LFACA","LMAHN","LSABV","LMANE","LBAJD","LBAJE","LHAHV","LBAJC","LBAIU","LMAMR","LHAAE","LHAAJ","LMAMW","LBAIL","LMABP","LSABU","LMAMX","LBAIN","LHAHM","LBAIR","LHACQ","LMAMC","LBAGO","LBAGP","LBAGN","LBAIK","LBAHY","LMAMM","LSABT","LHAHD","LBAIB","LMAMA","LHAAC",""]}