{"PhotonId":"4C490E7E2B095D7","UserName":"LIPLEIA","AccountCreationDate":"2022-12-28","PlayerProps":{"didTutorial":true},"AllowedCosmetics":["LHABO","LBAJB","LHAAN","LFAEW","LBAJC","LBAIQ","LBAIU","LFAES","LBAIR","LBAAJ","LBAIK","LHAAZ","LBAHY","LFAAC","LBAHV","LBAAC","LBAHP","LFAEF","LBAHF","LHAAD","LHAAS","LBAGO","LBAGY","LHAAA","LBAGN","LBAGT","LFADK","LBAEO","LFADG","LFADF","LBAEA","LFACS","LBADS","LHAEI","LHABZ","LHADZ","LBADC","LHAAQ","LBADB","LMAAR","LBABH","LBACT","LHAAP","LBACQ","LMACT","LFAAN","LBAAB","LHAAL","LFAAM","LFAAL","LFABX","LHAAC",""]}