{"PhotonId":"C0579836A7D882CE","UserName":"LITTLETIMMY","AccountCreationDate":"2023-12-25","PlayerProps":{"didTutorial":true},"AllowedCosmetics":["LBAJB","LBAJJ","LSAAE","LFAAX","LHABD","LBAJC","LBAIU","LBAIR","LBAIK","LBAHV","LBAHP","LBAHF","LBAGY","LMAFG","LBAGT","LBAGP","LBAGO","LBAGN","LMAAK","LBAGE","LHABZ","LFABE","LBAGD","LHADY","LFACK","LHAFS","LSABH","LMAIQ","LHAFQ","LBAFS","LBAFV","LMADD","LMAII","LMAIN","LMAIG","LBAFI","LHAFK","LSABG","LBAFL","LBAFN","LMAIL","LBAET","LHAAP","LHAAC","LFADK","LBAEO",""]}