{"PhotonId":"D6FA526DD796B91B","UserName":"MCDANGER","AccountCreationDate":"2023-03-31","PlayerProps":{"didTutorial":true},"AllowedCosmetics":["LBACP","LMAOL","LHAIA","LMAOG","LBAJN","LDAAD","LDAAD","LBAJO","LBAJB","LBAJJ","LDAAB","LFAEW","LMAHN","LMAHM","LMACI","LSABV","LMANE","LBAJD","LBAJE","LHAHV","LMALX","LMALX","LBAJC","LMALW","LMALW","LBAIU","LMAMC","LBAIR","LBAIK","LHACJ","LFABS","LHAAU","LMABC","LSABT","LHAHD","LBAIB","LMAMA","LBAHY","LBAHV","LMALO","LFAEH","LBAHP","LBAHP","LMAGC","LHAGP","LMAKX","LSABP","LBAHE","LFAED","LMALH","LBAHF","LMAFR","LFAEB","LMAFO","LSABO","LFAEC","LBAHB","LMAKT","LBAGY","LBAGX","LFABN","LMAKJ","LSABM","LHAGF","LBAGU","LBAAG","LHAAR","LBAGT","LMAES","LBADK","LMAJY","LBAGP","LBAGO","LBAGN","LMAJM","LMADS","LBAGE","LFABE","LHAFY","LHACR","LSABJ","LHAFW","LBAFY","LMAJB","LSABI","LMAJA","LBAGD","LHABW","LHAFU","LBAFX","LFACK","LHAFQ","LMAIQ","LSABH","LBAFS","LBAFV","LHAFO","LMADI","LFACF","LSAAT","LMAII","LHAFK","LSABG","LMAIG","LBAFI","LBAFL","LMAIL","LBAFN","LMACP","LMAHX","LFABB","LHAFI","LBAEU","LSABF","LHAFJ","LMAHU","LBAET","LHABF","LHABG","LHABE","LBACI","LSAAQ","LHADF","LSAAP","LHADE","LBACH","LFABZ","LHAFG","LSABE","LMAHJ","LBAES","LFADK","LBAEO","LBAEJ","LHAFC","LFAAV","LMABK","LHACP","LBAEK","LHAEZ","LMAHA","LMABM","LMABE","LBAAQ","LMAGS","LBAEI","LBAEG","LHAEW","LBAEF","LHAEV","LMAGR","LSABD","LFADF","LHAET","LBAEE","LMAGP","LMAGQ","LMAGH","LMAGG","LFADE","LBAEB","LBAEA","LMABT","LHACW","LHACS","LMABW","LFAAL","LMAFT","LMAFY","LFADC","LSABC","LHAEM","LBADV","LMAFN","LHAAP","LFAAI","LFAAH","LFACU","LBADS","LHAAL","LHAAE","LBAAB","LHAAC","LBADB",""]}