{"PhotonId":"A8A128AA32545C26","UserName":"MRELF","AccountCreationDate":"2024-01-26","PlayerProps":{"didTutorial":true},"AllowedCosmetics":["LBAJB","LHAAJ","LHAAF","LSAAE","LFAAX","LHABD","LMACL","LMACK","LFAEW","LHABG","LFABW","LHAAZ","LBAHV","LHAAB","LFADA","LBAHF","LBAAC","LBACD","LBAAJ","LMAAN","LHAAR","LBAGT","LHAAK","LBADL","LBADK","LHAAN","LBAGN","LBAGO","LBAGP","LHAAM","LBAAB","LBAGE","LFABE","LHACX","LHAAE","LHAAQ","LBAGD","LHAAO","LMAIR","LHABC","LFAAL","LFAAH","LBAFV","LHACY","LHAAP","LHAAL","LHABP","LHAAC","LFAAG","LBACS","LBAAW","LBAFI","LHAFK","LSABG","LMAIG","LHABR","LBACA","LHAAD",""]}