{"PhotonId":"ABCF9CCE31673BCC","UserName":"NERDGT","AccountCreationDate":"2022-12-25","PlayerProps":{"didTutorial":true},"AllowedCosmetics":["LBAJC","LBAJF","LFAEY","LMANQ","LSABW","LHAHY","LBAJI","LBAJH","LMAMR","LMAMM","LMANM","LFAEW","LBAFR","LHAAG","LMACB","LSABV","LMANE","LBAJD","LBAJE","LHAHV","LMAHK","LBAHV","LBAGD","LFABG","LBAFV","LFADK","LFABZ","LBACH","LSAAP","LHADE","LMACK","LSABE","LHAFG","LMAHJ","LBAES","LBAEO","LHAEZ","LFAAP","LBAAL","LHAAV","LSAAA","LFAAR","LFAAQ","LMAAX","LHAAW","LBAAM","LSAAB","LFAAS","LHAAX","LSAAC","LBAAN","LFAAT","LMAGU","LMAGZ","LBAEG","LHAEV","LBAEF","LMAGR","LSABD","LFADF","LBAEB","LBAEA","LMAGO","LMAGJ","LMABV","LMABT","LHAAS","LMADS","LHAEO","LFADA","LFADC","LMAGC","LBADB","LBADS","LFACW","LBADT","LMAFL","LHAAJ","LMAFN","LBADV","LSABC","LHAEM","LMAAM","LFAAF","LBADK","LMAAF","LHAAK","LMAEO","LBADJ","LFACN","LSABA","LFAAL","LHAAE","LBAAG","LFAAA","LBADC","LHAAC","LFAAN","LBAAB","LHAAP","LHACV",""]}