{"PhotonId":"4D7E7E94485731E8","UserName":"PENGU","AccountCreationDate":"2023-09-18","PlayerProps":{"BarkVersion":"1.5.1","void_menu_rot":395521824,"didTutorial":true,"BarkPlayerSize":1.0,"void_menu_open":false,"void_menu_pos":4266608697212328772,"BarkEnabledModules":{"Airplane":false,"Bubble":false,"Fly":false,"Grappling Hooks":false,"Nail Gun":false,"Rockets":false,"Speed Boost":false,"Wall Run":false,"Zipline":false,"Gravity":false,"No Collide":false,"No Slip":false,"Potions":false,"Slippery Hands":false,"Checkpoint":false,"Pearl":false,"Teleport":false,"Boxing":false,"Piggyback":false,"Telekinesis":false,"Fireflies":false,"X-Ray":false,"Join Bark Code":false,"Halo":false}},"AllowedCosmetics":[""]}