{"PhotonId":"21094C0D50570595","UserName":"PENGUINI","AccountCreationDate":"2023-12-31","PlayerProps":{"didTutorial":true},"AllowedCosmetics":["ITEMS","LMAEU","LBADL","LMAEN","LMAEQ","LSABL","LBAGL","LHAGD","LMAJV","LBAGO","LBAGN","LBAGP","LMAJQ","LSABK","LBAGF","LHAGB","LBAGE","LHACU","LBACC","LSAAN","LMABR","LMABT","LHAAI","LBAGB","LHAFY","LHAAP","LFADS","LMAJF","LBAEY","LBAGA","LMAJC","LBAGC","LFADT","LSABJ","LHAFW","LBAFY","LMAJB","LBAGD","LMAJA","LSABI","LMAED","LMADW","LHAAE","LBAAF","LHAAG","LHAAL","LHAFU","LMAIQ","LHAFQ","LBAFS","LSABH","LBAFV","LHADQ","LMADB","LMAII","LMAIH","LHAFK","LBAFI","LSABG","LMAIG","LFAAN","LBAFL","LBAFN","LMAIL","LHAAC","LHACY","LBAAC","LFAAL","LMAHY","LBAET","LHAAD","LBAAB","LFADK","LBAEO",""]}