{"PhotonId":"C3BA0D9A82CF74AE","UserName":"PLUTOVR","AccountCreationDate":"2021-12-30","PlayerProps":{"didTutorial":true},"AllowedCosmetics":["ITEMS","LBAGN","LBAGO","LBAGP","LBAGH","LBAGE","LBAFL","LBAFN","LMAIL","LHABI","LBAET","LBAEO","LBAEN","LFADF","LBAAF","LBACD","LMAFX","LBADS","LHAAJ","LBABI","LHAAS","LMACT","LBACE","LMACJ","LHADG","LFABX","LBABH","LFAAW","LMABO","LHAAZ","LHAAU","LMAAZ","LHABP","LHAAF","LBAAJ","LHAAR","LFABN","LFAAH","LFAAL","LHAAQ","LHAAE","LMAAL","LHAAI","LFABH","LHABC","LBABG","LFABF","LHAAG","LFAAG","LFAAA","LBAAC","LHAAC","LBAAB","LHAAD","LBABA","LBAAZ","LFAAF","LFABB","LHAAB","LFABA","Early Access Supporter PackLBAAE","LFAAM","LFAAN","LHAAA","LHAAK","LHAAL","LHAAM","LHAAN","LHAAO","LHAAP","LHABA","LHABB",""]}