{"PhotonId":"E4960A6FBD1256D8","UserName":"POOPY09","AccountCreationDate":"2024-03-24T21:25:19.46Z","PlayerProps":{"BarkEnabledModules":{"Airplane":false,"Bubble":false,"Fly":false,"Grappling Hooks":false,"Nail Gun":false,"Rockets":false,"Speed Boost":true,"Wall Run":false,"Zipline":false,"Gravity":false,"No Collide":false,"No Slip":false,"Potions":true,"Slippery Hands":false,"Checkpoint":false,"Pearl":false,"Teleport":false,"Boxing":false,"Piggyback":false,"Telekinesis":false,"Fireflies":false,"X-Ray":false,"Join Bark Code":false,"Halo":false},"BarkPlayerSize":0.501890838,"didTutorial":true,"BarkVersion":"1.5.1"},"AllowedCosmetics":["ITEMS","LHADY","LHABC","S"," FIRST LOGIN"]}