{"PhotonId":"4A8E1623A7D21234","UserName":"PPPTIG","AccountCreationDate":"2022-12-26","PlayerProps":{"didTutorial":true},"AllowedCosmetics":["LBAJB","LFADL","LBAJJ","LMANI","LFAEW","LSABV","LMANE","LBAJD","LBAJE","LHAHV","LBAJC","LBAIU","LBAAP","LBAIR","LBAIK","LSAAC","LHAAX","LFAAT","LBAAN","LBAHY","LHAAZ","LBAHP","LBAHV","LFACX","LHAAK","LBAGP","LBAGN","LBAGO","LBAGD","LMAIW","LBAFV","LMAIL","LBAFN","LBAFL","LHABH","LBAET","LFAAX","LHABD","LSAAE","LFADK","LBAEO","LFAAW","LBAEN","LHAEL","LMAAM","LHAAN","LBADK","LHAAB","LFAAM","LHAEB","LFACL","LHAAM","LMAAR","LBADC","LBAAB","LBABH","LMADU","LMABP","LBADB","LHABI","LFAAH","LSAAT","LMADI","LFACF","LBAAJ","LBACT","LBAAC","LMACT","LBACQ","LHAAL","LFAAL","LHAAD","LHAAE","LHAAC","LFABX","LBACD",""]}