{"PhotonId":"533098724A5EA4D3","UserName":"RANDO","AccountCreationDate":"2022-12-29","PlayerProps":{"didTutorial":true},"AllowedCosmetics":["LHAHW","LFAEW","LMANO","LMAMM","LBAHP","LBAHV","LHAAI","LBAHF","LFACW","LBAGY","LMAKJ","LBAGT","LBAGP","LBAGO","LBAGN","LMAJN","LBAGE","LMABT","LMAJH","LBAGD","LHAFS","LMAIR","LBAFV","LBAFN","LMAIL","LBAFL","LMAHV","LBAET","LBAEU","LSABF","LHAFJ","LMAHU","LMAHN","LFADK","LBAEO","LFABW","LMAGX","LFADF","LBAEB","LBAEA","LMAGA","LBADS","LFAAH","LMAFA","LMABD","LBAAB","LBADC","LHAAP","LMADT","LMADR","LMADL","LSAAU","LBADB","LHAAE","LHAAC","LBACA","LBACT","LMACY","LMACT","LBACQ","LFABX",""]}