{"PhotonId":"411DF962A0DB43EC","UserName":"RATATOUILLE","AccountCreationDate":"2022-01-23","PlayerProps":{"didTutorial":true},"AllowedCosmetics":["LBAGN","LBAGO","LBAGP","LFACK","LBAFV","LMACY","LBAFL","LBAFN","LMAIL","LHABI","LBAET","LMACK","LFADK","LBAEO","LHAAS","LFADF","LHAAN","LBADC","LFAAA","LHABP","LHAAJ","LBACT","LMABP","LBACQ","LMACT","LHAAP","LMAAT","LMAAZ","LHAAB","LHAAL","LFABN","LFAAC","LFAAH","LFAAN","LBAAB","LHAAQ","LFABH","LHAAK","LFABF","LHAAC","LHAAM","LBABA","LBAAZ","LHAAD","LFABB",""]}