{"PhotonId":"3FABD194D65E72BF","UserName":"RUNSRTGGG","AccountCreationDate":"2022-12-27","PlayerProps":{"didTutorial":true},"AllowedCosmetics":["LBAAC","LBAJC","LBAHV","LBAHY","LMALU","LFABR","LFAAG","LBAGD","LHABV","LMAIL","LBAFN","LBAFL","LHABL","LFABB","LBAET","LBAAR","LMACK","LMACH","LFADK","LBAEO","LBAAB","LHAAP","LBAAP","LFAAW","LMAAY","LSAAA","LHAAV","LBAAL","LFAAR","LFAAT","LSAAC","LBAAN","LHAAX","LHAAZ","LFAAQ","LFADH","LBAAJ","LFADF","LFAAH","LBAEB","LBAEA","LFAAL","LFAAI","LBAAA","LBAAG","LBAAH","LBADS","LHAAE","LHAAC","LHAAL","LFAAN","LBADC","LHAAN","LBADB","LHACY","LBACT","LFABX",""]}