{"PhotonId":"45D38816FF639BD6","UserName":"SKYZVR","AccountCreationDate":"2022-01-14","PlayerProps":{"didTutorial":true},"AllowedCosmetics":["ITEMS","LHAEB","LBAGN","LBAGO","LBAGP","LBAGE","LFADC","LBADS","LFABO","LHAAB","LHAED","LBADB","LBACT","LMAAP","LHADC","LSAAR","LFACA","LBACK","LMACD","LMACI","LHADA","LSAAP2","LMABZ","LBACF","LFABX","LMABO","LHACK","LMAAZ","LFABN","LHAAJ","LFAAF","LFABH","LBAAA","LBABL","LBABH","LFABF","LHAAR","LFAAH","LFAAA","LBABA","LBAAZ","LHAAD","Early Access Supporter PackLFAAL","LHAAC","LBAAB","LBAAE","LFAAM","LFAAN","LHAAA","LHAAK","LHAAL","LHAAM","LHAAN","LHAAO","LHAAP","LHABA","LHABB",""]}