{"PhotonId":"BC7A791A1F8D7DD6","UserName":"SLIME","AccountCreationDate":"2023-12-25","PlayerProps":{"didTutorial":true},"AllowedCosmetics":["LBAJB","LMANF","LBAJC","LMANK","LMAHM","LSABV","LMANE","LBAJD","LBAJE","LHAHV","LFAEW","LHAHQ","LDAAB","LBAIU","LBAIR","LMAMM","LBAIK","LHAET","LBAHY","LBAHV","LMALU","LFAAL","LBAHP","LBAHH","LFAEG","LBAHF","LFACZ","LFACS","LBAGY","LMAKF","LSABN","LBAGT","LMABP","LHACY","LBAGN","LBAGO","LBAGP","LBAGE","LHABS","LHAAM","LBAGD","LHAFR","LBAFV","LBAFL","LBAFN","LMAIL","LHAAL","LBACA","LHAAP","LBAET","LBADB","LHAAE","LBAAB","LHAAC","LBAEO",""]}