{"PhotonId":"DB8370DB6BA0D420","UserName":"STFUN","AccountCreationDate":"2023-01-04","PlayerProps":{"didTutorial":true},"AllowedCosmetics":["LBAGP","LMAOG","LBAJN","LDAAD","LFABB","LBAJB","LBAJF","LFAEW","LMALU","LBAHV","LHAAZ","LBAGO","LBAGN","LHAAR","LBAGD","LHAFV","LFAAA","LBAFV","LBAFB","LMAIL","LBAFN","LFADL","LBAET","LFADM","LHAAA","LFADK","LBAEO","LFAAF","LFADF","LBAEB","LBAEA","LHAAL","LHAAP","LBAAB","LHAAQ","LHAAE","LBADS","LBADB","LFAAH","LHACZ","LBADL","LFACL","LBADC","LHABP","LMADM","LMADU","LHAAC","LHAAM","LMABP","LHACV","LBACA","LBACQ","LMACT","LMAAP","LFAAN",""]}