{"PhotonId":"D0AAFE45A625E183","UserName":"SUN","AccountCreationDate":"2022-06-30","PlayerProps":{"didTutorial":true},"AllowedCosmetics":["LBAJB","LFAEX","LHAHX","LBAJJ","LHAHW","LDAAC","LFAEV","LFAEW","LSABV","LMANE","LBAJD","LBAJE","LHAHV","LHACY","LBAJC","LHADD","LDAAB","LBAIU","LHAHL","LBAIR","LBAAJ","LBAIK","LFAAP","LBAHY","LFAEL","LMALU","LHAHA","LBAHV","LBAHP","LFADA","LSABQ","LMALI","LHAGS","LBAFR","LBAHF","LMAFM","LSABN","LFACU","LMAKU","LHAGL","LBAGZ","LSABO","LFAEC","LBAHB","LBAGY","LHAAF","LBADQ","LFABO","LHABC","LBAGT","LMAJY","LBAGP","LBAGO","LBAGN","LBAGH","LBAGE","LHABS","LMAJA","LSABI","LBAGD","LFAAF","LBAFV","LBAFK","LBAFD","LBAFB","LBAFL","LMAIL","LBAFN","LBAFC","LBAET","LFABA","LHABP","LMAHN","LSABE","LHAFG","LBAES","LMAHJ","LBAEO","LMABI","LBAEJ","LMAHB","LFABS","LSAAD","LFAAU","LHAAY","LBAAO","LBAEF","LSABD","LHAEV","LMAGR","LFAAR","LBAAL","LHAAV","LSAAA","LMAGX","LBAEH","LHAEY","LFADF","LMAGS","LHAAB","LMAGL","LBAEB","LFADE","LBAEA","LMAFN","LHAEM","LBADV","LSABC","LFADC","LHAEO","LHAAJ","LHAAR","LBADS","LFACS","LHAAS","LBADM","LBACA","LMAET","LHAEC","LFACN","LMAEO","LSABA","LBADJ","LBABE","LHADY","LBADC","LHABV","LBABJ","LBADB","LBACZ","LHADV","LSAAX","LMADS","LHABI","LBAAT","LHABL","LFABB","LSAAU","LMADL","LBAAG","LBAAF","LHADQ","LBACT","LHABR","LBAAU","LBAAX","LMACT","LBACQ","LFAAJ","LMACP","LHADK","LHAAE","LHAAD","LSAAE","LFAAX","LHABD","LBAAS","LHABF","LFABY","LMACJ","LFAAA","LMACI","LMACC","LSAAQ","LHADF","LBACI","LFABX","LHACX","LMABS","LMABV","LMABT","LBACF","LMABZ","LSAAP2","LHADA","Early Access Supporter PackLFAAL","LFAAN","LBAAB","LHAAQ","LMABN","LFAAV","LHAAP","LMABE","LMABF","LFAAI","LMABO","LFAAG","LSAAC","LBAAN","LHAAX","LFAAT","LMABC","LMAAZ","LHACK","LMAAX","LHAAL","LHAAC","LBAAE","LFAAM","LFAAN","LHAAA","LHAAK","LHAAL","LHAAM","LHAAN","LHAAO","LHAAP","LHABA","LHABB",""]}