{"PhotonId":"EBB894963BC565FB","UserName":"TBASH","AccountCreationDate":"2025-01-09","PlayerProps":{"GratePlayerSize":1.0,"GrateEnabledModules":{"Return To VStump":false,"Airplane":false,"Bubble":false,"Fly":false,"Grappling Hooks":false,"Climb":false,"Double Jump":false,"Platforms":false,"Nail Gun":false,"Rockets":false,"Speed Boost":false,"Swim":false,"Wall Run":false,"Zipline":false,"Gravity":false,"No Clip":false,"No Slip":false,"Potions":false,"Slippery Hands":false,"Checkpoint":false,"Portals":false,"Pearl":false,"Teleport":false,"Boxing":false,"Piggyback":false,"Telekinesis":false,"Fireflies":false,"ESP":false,"Halo":false},"genesis":true,"didTutorial":true,"GrateVersion":"1.6.0"},"AllowedCosmetics":["LHAAO","LBAJJ","LHAAC","LMANM","LHAAP","S"," FIRST LOGIN"]}