{"PhotonId":"40C124B4207046E6","UserName":"THATBLIZZY","AccountCreationDate":"2022-07-18","PlayerProps":{"didTutorial":true},"AllowedCosmetics":["LHAAO","LFAEW","LBAFR","LBAIU","LBAJC","LFABS","LSAAA","LHAAV","LFAAR","LBAAL","LSAAC","LHAAX","LFAAT","LBAAN","LSAAB","LHAAW","LFAAS","LBAAM","LSABT","LHAHD","LBAIB","LMAMA","LBAEJ","LBAAQ","game-purchase-bundleLFAEE","LSAAF","LBABS","LHACH","LBAHF","LMAGC","LBABP","LFACP","LSABM","LHAGF","LBAGU","LBADO","LBAGT","LFAAB","LHAAB","LBAGN","LBAGO","LBAGP","LBACD","LBAGE","LHADQ","LBAFN","LBAFL","LMAIL","LHABF","LFADK","LBAEO","LHAAT","LFADF","LBAEB","LHAAK","LBAEA","LFADC","LHAAS","LBADS","LBAAF","LBAAA","LFABI","LHABP","LBADL","LHAED","LBADB","LFABE","LBADC","LFABF","LBACT","LBACQ","LMACT","LFAAF","LHAAE","LHAAN","LFABX","LMABY","LBAAP","LMABO","LBAAC","LFAAQ","LMAAZ","LHAAD","LFAAN","LFAAA","LFAAL","LHAAL","LHAAC","LBAAB","LHAAP","LFABN",""]}