{"PhotonId":"4C3326D3AB572405","UserName":"VPRSOARGT","AccountCreationDate":"2022-08-09","PlayerProps":{"didTutorial":true},"AllowedCosmetics":["LBAJB","LHAHX","LBAJJ","LMANP","LFAEW","LDAAB","LHADD","LBAIU","LBAJC","LBAHY","LBAHV","LBAHP","LBAHF","LBAGN","LBAGO","LBAGP","LFABI","LSABI","LMAJA","LBAFV","LBAFL","LMAIL","LBAFN","LHABI","LBAEO","LFADK","LFADH","LFADF","LBAEA","LBAEB","LFADE","LFACT","LBADS","LFAAA","LFABE","LBADC","LBADB","LBAAA","LHAAB","LBACT","LFAAF","LHABP","LHABR","LHAAJ","LMACT","LBACQ","LHABC","LFAAX","LHABD","LSAAE","LFABA","LHABG","LHABF","LBAAR","LHAAN","LFABX","LHACZ","LHAAA","LFAAL","LHAAK","LHAAE","LBAAC","LHAAD","LHAAF","LHAAS","LHAAM","LMABZ","LSAAP2","LBACF","LHADA","LBAAP","LMABO","LHAAC","LBAAB","LHAAP","LHAAR","LHAAU","LMABA","LFAAT","LHAAX","LSAAC","LBAAN","LMAAX","LHACJ","LMAAZ","LHAAL",""]}